LICENSE.txt
README.md
setup.cfg
setup.py
JFSmallThread/__init__.py
JFSmallThread/boundedQueueThreadPool.py
JFSmallThread/httpPool.py
JFSmallThread/rapidlyThreadPool.py
JFSmallThread/tpsThreadPool.py
JFSmallThread.egg-info/PKG-INFO
JFSmallThread.egg-info/SOURCES.txt
JFSmallThread.egg-info/dependency_links.txt
JFSmallThread.egg-info/requires.txt
JFSmallThread.egg-info/top_level.txt
JFSmallThread/contrib/__init__.py