Metadata-Version: 2.1
Name: JFSmallThread
Version: 1.0.0
Summary: 飞快的请求库
Home-page: UNKNOWN
Author: LiuJunFeng
Author-email: 
License: MIT
Platform: UNKNOWN
Requires-Python: >=3.7,<4
License-File: LICENSE.txt
